<Stations>
  <Station>
    <ID>0</ID>
    <Label>-</Label>
    <JobTypeID>1</JobTypeID>
  </Station>
  <Station>
    <ID>2</ID>
    <Label>ELEM2</Label>
    <JobTypeID>1</JobTypeID>
  </Station>
  <Station>
    <ID>3</ID>
    <Label>ELEM1</Label>
    <JobTypeID>5</JobTypeID>
  </Station>
  <Station>
    <ID>4</ID>
    <Label>ELEM2</Label>
    <JobTypeID>5</JobTypeID>
  </Station>
  <Station>
    <ID>5</ID>
    <Label>S1</Label>
    <JobTypeID>2</JobTypeID>
  </Station>
  <Station>
    <ID>6</ID>
    <Label>S2</Label>
    <JobTypeID>2</JobTypeID>
  </Station>
  <Station>
    <ID>7</ID>
    <Label>S3</Label>
    <JobTypeID>2</JobTypeID>
  </Station>
  <Station>
    <ID>8</ID>
    <Label>S4</Label>
    <JobTypeID>2</JobTypeID>
  </Station>
  <Station>
    <ID>9</ID>
    <Label>S6</Label>
    <JobTypeID>2</JobTypeID>
  </Station>
  <Station>
    <ID>10</ID>
    <Label>S5</Label>
    <JobTypeID>2</JobTypeID>
  </Station>
  <Station>
    <ID>11</ID>
    <Label>S7</Label>
    <JobTypeID>4</JobTypeID>
  </Station>
  <Station>
    <ID>12</ID>
    <Label>S8</Label>
    <JobTypeID>4</JobTypeID>
  </Station>
  <Station>
    <ID>13</ID>
    <Label>S9</Label>
    <JobTypeID>4</JobTypeID>
  </Station>
  <Station>
    <ID>14</ID>
    <Label>S10</Label>
    <JobTypeID>4</JobTypeID>
  </Station>
  <Station>
    <ID>15</ID>
    <Label>S11</Label>
    <JobTypeID>4</JobTypeID>
  </Station>
  <Station>
    <ID>16</ID>
    <Label>S12</Label>
    <JobTypeID>4</JobTypeID>
  </Station>
  <Station>
    <ID>17</ID>
    <Label>ELEM1</Label>
    <JobTypeID>1</JobTypeID>
  </Station>
</Stations>