<UniqueJob>
  <Job>
    <JobBase>
      <ID>60</ID>
      <Status>Test</Status>
      <EngID>99972</EngID>
      <CrossAppEngID>99999</CrossAppEngID>
      <Name>EngTest2</Name>
      <JobNum>2016005002</JobNum>
      <PO>3000454</PO>
      <ShipDate>1/1/0001 12:00:00 AM</ShipDate>
      <LatestFinishDate>1/1/0001 12:00:00 AM</LatestFinishDate>
      <Cust>5</Cust>
      <Contractor>eliud</Contractor>
      <JobTypeID>1</JobTypeID>
      <CityID>36</CityID>
      <FireCodeID>18</FireCodeID>
    </JobBase>
    <JobExtension>
      <ID>60</ID>
      <JobID>60</JobID>
      <NumOfStops>4</NumOfStops>
      <JobTypeMain>Simplex</JobTypeMain>
      <JobTypeAdd>Selective Collective</JobTypeAdd>
      <InputVoltage>208</InputVoltage>
      <InputPhase>3</InputPhase>
      <InputFrecuency>60</InputFrecuency>
      <DoorGate>Manual</DoorGate>
      <DoorHoist>Automatic</DoorHoist>
      <SHCRisers>3</SHCRisers>
      <DoorOperatorID>2</DoorOperatorID>
      <InfDetector>False</InfDetector>
      <MechSafEdge>False</MechSafEdge>
      <HeavyDoors>False</HeavyDoors>
      <CartopDoorButtons>False</CartopDoorButtons>
      <DoorHold>False</DoorHold>
      <Nudging>False</Nudging>
      <SCOP>True</SCOP>
      <SHC>True</SHC>
      <AUXCOP>False</AUXCOP>
    </JobExtension>
    <HydroSpecific>
      <ID>33</ID>
      <JobID>60</JobID>
      <Starter>Siemens SS : 3/9</Starter>
      <HP>15</HP>
      <FLA>27</FLA>
      <SPH>120</SPH>
      <MotorsNum>4</MotorsNum>
      <MotorsDisconnect>3</MotorsDisconnect>
      <ValveBrand>Maxton</ValveBrand>
      <ValveCoils>3</ValveCoils>
      <ValveNum>4</ValveNum>
      <ValveVoltage>3</ValveVoltage>
      <BatteryBrand>Nulo</BatteryBrand>
      <Battery>False</Battery>
      <LifeJacket>False</LifeJacket>
      <LOS>False</LOS>
      <OilCool>False</OilCool>
      <OilTank>False</OilTank>
      <PSS>False</PSS>
      <Resync>True</Resync>
      <VCI>True</VCI>
    </HydroSpecific>
    <GenericFeatures>
      <ID>32</ID>
      <JobID>60</JobID>
      <EPCarsNumber>Nulo</EPCarsNumber>
      <EPContact>Nulo</EPContact>
      <TopAccessLocation>Nulo</TopAccessLocation>
      <BottomAccessLocation>Nulo</BottomAccessLocation>
      <INCPButtons>Nulo</INCPButtons>
      <SwitchStyle>Nulo</SwitchStyle>
      <GovModel>Nulo</GovModel>
      <Monitoring>Nulo</Monitoring>
      <CarCallCodeSecurity>Nulo</CarCallCodeSecurity>
      <SpecialInstructions>Nulo</SpecialInstructions>
      <FRON2>True</FRON2>
      <Attendant>True</Attendant>
      <CarToLobby>True</CarToLobby>
      <EQ>False</EQ>
      <EMT>False</EMT>
      <EP>False</EP>
      <EPVoltage>False</EPVoltage>
      <EPOtherCars>False</EPOtherCars>
      <PTI>False</PTI>
      <EPSelect>False</EPSelect>
      <FLO>False</FLO>
      <Hosp>False</Hosp>
      <Ind>False</Ind>
      <INA>False</INA>
      <TopAccess>False</TopAccess>
      <BottomAccess>False</BottomAccess>
      <INCP>False</INCP>
      <LoadWeigher>False</LoadWeigher>
      <CTINSPST>False</CTINSPST>
      <Roped>False</Roped>
      <CallEnable>False</CallEnable>
      <CarCallRead>False</CarCallRead>
      <HallCallRead>False</HallCallRead>
      <CarKey>False</CarKey>
      <HallKey>False</HallKey>
      <CRO>False</CRO>
      <HCRO>False</HCRO>
    </GenericFeatures>
    <Indicator>
      <ID>23</ID>
      <JobID>60</JobID>
      <CarCallsVoltage>24</CarCallsVoltage>
      <CarCallsVoltageType>DC</CarCallsVoltageType>
      <CarCallsType>LED</CarCallsType>
      <HallCallsVoltage>24</HallCallsVoltage>
      <HallCallsVoltageType>DC</HallCallsVoltageType>
      <HallCallsType>LED</HallCallsType>
      <CarPIType>Emotive</CarPIType>
      <CarPIDiscreteType>Multi-light</CarPIDiscreteType>
      <HallPIType>CE Electronics</HallPIType>
      <HallPIDiscreteType>Multi-light</HallPIDiscreteType>
      <VoiceAnnunciationPIType>CE Electronics</VoiceAnnunciationPIType>
      <CarLanternsStyle>CE Electronics</CarLanternsStyle>
      <CarLanternsType>Gong</CarLanternsType>
      <HallLanternsStyle>CE Electronics</HallLanternsStyle>
      <HallLanternsType>Gong</HallLanternsType>
      <PassingFloorType>CE Electronics</PassingFloorType>
      <PassingFloorDiscreteType>Chime</PassingFloorDiscreteType>
      <IndicatorsVoltage>24</IndicatorsVoltage>
      <IndicatorsVoltageType>DC</IndicatorsVoltageType>
      <CarPI>False</CarPI>
      <HallPI>False</HallPI>
      <VoiceAnnunciationPI>False</VoiceAnnunciationPI>
      <CarLanterns>False</CarLanterns>
      <HallLanterns>False</HallLanterns>
      <PassingFloor>False</PassingFloor>
      <PassingFloorEnable>False</PassingFloorEnable>
    </Indicator>
    <HoistWayData>
      <ID>28</ID>
      <JobID>60</JobID>
      <HoistWaysNumber>4</HoistWaysNumber>
      <MachineRooms>5</MachineRooms>
      <Capacity>3</Capacity>
      <UpSpeed>105</UpSpeed>
      <DownSpeed>200</DownSpeed>
      <TotalTravel>5</TotalTravel>
      <LandingSystemID>2</LandingSystemID>
      <FrontFirstServed>True</FrontFirstServed>
      <RearFirstServed>False</RearFirstServed>
      <FrontSecondServed>True</FrontSecondServed>
      <RearSecondServed>False</RearSecondServed>
      <FrontThirdServed>True</FrontThirdServed>
      <RearThirdServed>False</RearThirdServed>
      <FrontFourthServed>True</FrontFourthServed>
      <RearFourthServed>False</RearFourthServed>
      <FrontFifthServed>True</FrontFifthServed>
      <RearFifthServed>False</RearFifthServed>
      <FrontSexthServed>False</FrontSexthServed>
      <RearSexthServed>True</RearSexthServed>
      <FrontSeventhServed>True</FrontSeventhServed>
      <RearSeventhServed>True</RearSeventhServed>
      <FrontEightServed>True</FrontEightServed>
      <RearEightServed>False</RearEightServed>
      <FrontNinthServed>True</FrontNinthServed>
      <RearNinthServed>False</RearNinthServed>
      <FrontTenthServed>False</FrontTenthServed>
      <RearTenthServed>False</RearTenthServed>
      <FrontEleventhServed>False</FrontEleventhServed>
      <RearEleventhServed>False</RearEleventhServed>
      <FrontTwelvethServed>False</FrontTwelvethServed>
      <RearTwelvethServed>False</RearTwelvethServed>
      <FrontThirteenthServed>False</FrontThirteenthServed>
      <RearThirteenthServed>False</RearThirteenthServed>
      <FrontFourteenthServed>False</FrontFourteenthServed>
      <RearFourteenthServed>False</RearFourteenthServed>
      <FrontFifteenthServed>False</FrontFifteenthServed>
      <RearFifteenthServed>False</RearFifteenthServed>
      <FrontSixteenthServed>False</FrontSixteenthServed>
      <RearSixteenthServed>False</RearSixteenthServed>
    </HoistWayData>
    <SpecialFeatures />
  </Job>
</UniqueJob>